latin_to_arabic_number.py
latin_to_arabic_number-0.0.3.dist-info/LICENSE
latin_to_arabic_number-0.0.3.dist-info/LICENSE.txt
latin_to_arabic_number-0.0.3.dist-info/METADATA
latin_to_arabic_number-0.0.3.dist-info/WHEEL
latin_to_arabic_number-0.0.3.dist-info/top_level.txt
latin_to_arabic_number-0.0.3.dist-info/RECORD
