Metadata-Version: 2.1
Name: latin-to-arabic-number
Version: 0.0.3
Summary: This library helps to reverse numbers order OR change latin numbers to arabic in a .docx file
Home-page: https://github.com/berkansems/latin_to_arabic_number
Author: berkan sems
Author-email: berkansems@gmail.com
License: UNKNOWN
Platform: UNKNOWN
Classifier: Programming Language :: Python :: 2.7
Classifier: Programming Language :: Python :: 3
Classifier: Programming Language :: Python :: 3.4
Classifier: Programming Language :: Python :: 3.5
Classifier: Programming Language :: Python :: 3.6
Classifier: Programming Language :: Python :: 3.7
Classifier: Programming Language :: Python :: 3.8
Classifier: Programming Language :: Python :: 3.9
Classifier: Programming Language :: Python :: 3.10
Requires-Dist: Document (>=0.8.11)
